[{
    "day": 1.0
    , "fajir": "4:00"
    , "fajirIqamah": "4:30"
    , "sunrise": "5:48"
    , "duhur": "1:16"
    , "duhurIqamah": "1:30"
    , "asr": "5:20"
    , "asrIqamah": "5:45"
    , "maghrib": "8:48"
    , "maghribIqamah": "8:55"
    , "isha": "10:30"
    , "ishaIqamah": "10:35"
}, {
    "day": 2.0
    , "fajir": "4:02"
    , "fajirIqamah": "4:30"
    , "sunrise": "5:49"
    , "duhur": "1:16"
    , "duhurIqamah": "1:30"
    , "asr": "5:19"
    , "asrIqamah": "5:45"
    , "maghrib": "8:46"
    , "maghribIqamah": "8:55"
    , "isha": "10:28"
    , "ishaIqamah": "10:35"
}, {
    "day": 3.0
    , "fajir": "4:04"
    , "fajirIqamah": "4:30"
    , "sunrise": "5:50"
    , "duhur": "1:16"
    , "duhurIqamah": "1:30"
    , "asr": "5:18"
    , "asrIqamah": "5:45"
    , "maghrib": "8:45"
    , "maghribIqamah": "8:55"
    , "isha": "10:26"
    , "ishaIqamah": "10:35"
}, {
    "day": 4.0
    , "fajir": "4:06"
    , "fajirIqamah": "4:30"
    , "sunrise": "5:42"
    , "duhur": "1:15"
    , "duhurIqamah": "1:30"
    , "asr": "5:18"
    , "asrIqamah": "5:45"
    , "maghrib": "8:43"
    , "maghribIqamah": "8:50"
    , "isha": "10:24"
    , "ishaIqamah": "10:30"
}, {
    "day": 5.0
    , "fajir": "4:08"
    , "fajirIqamah": "4:30"
    , "sunrise": "5:53"
    , "duhur": "1:15"
    , "duhurIqamah": "1:30"
    , "asr": "5:17"
    , "asrIqamah": "5:45"
    , "maghrib": "8:42"
    , "maghribIqamah": "8:50"
    , "isha": "10:21"
    , "ishaIqamah": "10:30"
}, {
    "day": 6.0
    , "fajir": "4:10"
    , "fajirIqamah": "4:30"
    , "sunrise": "5:54"
    , "duhur": "1:15"
    , "duhurIqamah": "1:30"
    , "asr": "5:16"
    , "asrIqamah": "5:45"
    , "maghrib": "8:40"
    , "maghribIqamah": "8:50"
    , "isha": "10:19"
    , "ishaIqamah": "10:30"
}, {
    "day": 7.0
    , "fajir": "4:12"
    , "fajirIqamah": "4:30"
    , "sunrise": "5:55"
    , "duhur": "1:15"
    , "duhurIqamah": "1:30"
    , "asr": "5:16"
    , "asrIqamah": "5:45"
    , "maghrib": "8:39"
    , "maghribIqamah": "8:50"
    , "isha": "10:17"
    , "ishaIqamah": "10:25"
}, {
    "day": 8.0
    , "fajir": "4:14"
    , "fajirIqamah": "4:30"
    , "sunrise": "5:57"
    , "duhur": "1:15"
    , "duhurIqamah": "1:30"
    , "asr": "5:15"
    , "asrIqamah": "5:45"
    , "maghrib": "8:37"
    , "maghribIqamah": "8:45"
    , "isha": "10:15"
    , "ishaIqamah": "10:25"
}, {
    "day": 9.0
    , "fajir": "4:15"
    , "fajirIqamah": "4:50"
    , "sunrise": "5:58"
    , "duhur": "1:15"
    , "duhurIqamah": "1:30"
    , "asr": "5:14"
    , "asrIqamah": "5:45"
    , "maghrib": "8:36"
    , "maghribIqamah": "8:40"
    , "isha": "10:13"
    , "ishaIqamah": "10:15"
}, {
    "day": 10.0
    , "fajir": "4:17"
    , "fajirIqamah": "4:50"
    , "sunrise": "5:59"
    , "duhur": "1:15"
    , "duhurIqamah": "1:30"
    , "asr": "5:13"
    , "asrIqamah": "5:45"
    , "maghrib": "8:34"
    , "maghribIqamah": "8:40"
    , "isha": "10:10"
    , "ishaIqamah": "10:15"
}, {
    "day": 11.0
    , "fajir": "4:19"
    , "fajirIqamah": "4:50"
    , "sunrise": "6:01"
    , "duhur": "1:14"
    , "duhurIqamah": "1:30"
    , "asr": "5:13"
    , "asrIqamah": "5:45"
    , "maghrib": "8:32"
    , "maghribIqamah": "8:40"
    , "isha": "10:08"
    , "ishaIqamah": "10:15"
}, {
    "day": 12.0
    , "fajir": "4:21"
    , "fajirIqamah": "4:50"
    , "sunrise": "6:02"
    , "duhur": "1:14"
    , "duhurIqamah": "1:30"
    , "asr": "5:12"
    , "asrIqamah": "5:45"
    , "maghrib": "8:31"
    , "maghribIqamah": "8:40"
    , "isha": "10:06"
    , "ishaIqamah": "10:15"
}, {
    "day": 13.0
    , "fajir": "4:23"
    , "fajirIqamah": "4:50"
    , "sunrise": "6:03"
    , "duhur": "1:14"
    , "duhurIqamah": "1:30"
    , "asr": "5:11"
    , "asrIqamah": "5:45"
    , "maghrib": "8:29"
    , "maghribIqamah": "8:40"
    , "isha": "10:03"
    , "ishaIqamah": "10:15"
}, {
    "day": 14.0
    , "fajir": "4:25"
    , "fajirIqamah": "4:50"
    , "sunrise": "6:05"
    , "duhur": "1:14"
    , "duhurIqamah": "1:30"
    , "asr": "5:10"
    , "asrIqamah": "5:45"
    , "maghrib": "8:27"
    , "maghribIqamah": "8:40"
    , "isha": "10:01"
    , "ishaIqamah": "10:15"
}, {
    "day": 15.0
    , "fajir": "4:27"
    , "fajirIqamah": "5:00"
    , "sunrise": "6:06"
    , "duhur": "1:14"
    , "duhurIqamah": "1:30"
    , "asr": "5:09"
    , "asrIqamah": "5:30"
    , "maghrib": "8:26"
    , "maghribIqamah": "8:40"
    , "isha": "9:59"
    , "ishaIqamah": "10:15"
}, {
    "day": 16.0
    , "fajir": "4:29"
    , "fajirIqamah": "5:00"
    , "sunrise": "6:07"
    , "duhur": "1:14"
    , "duhurIqamah": "1:30"
    , "asr": "5:08"
    , "asrIqamah": "5:30"
    , "maghrib": "8:24"
    , "maghribIqamah": "8:30"
    , "isha": "9:56"
    , "ishaIqamah": "10:00"
}, {
    "day": 17.0
    , "fajir": "4:31"
    , "fajirIqamah": "5:00"
    , "sunrise": "6:09"
    , "duhur": "1:13"
    , "duhurIqamah": "1:30"
    , "asr": "5:07"
    , "asrIqamah": "5:30"
    , "maghrib": "8:22"
    , "maghribIqamah": "8:30"
    , "isha": "9:54"
    , "ishaIqamah": "10:00"
}, {
    "day": 18.0
    , "fajir": "4:33"
    , "fajirIqamah": "5:00"
    , "sunrise": "6:10"
    , "duhur": "1:13"
    , "duhurIqamah": "1:30"
    , "asr": "5:06"
    , "asrIqamah": "5:30"
    , "maghrib": "8:20"
    , "maghribIqamah": "8:30"
    , "isha": "9:52"
    , "ishaIqamah": "10:00"
}, {
    "day": 19.0
    , "fajir": "4:34"
    , "fajirIqamah": "5:00"
    , "sunrise": "6:11"
    , "duhur": "1:13"
    , "duhurIqamah": "1:30"
    , "asr": "5:05"
    , "asrIqamah": "5:30"
    , "maghrib": "8:18"
    , "maghribIqamah": "8:30"
    , "isha": "9:49"
    , "ishaIqamah": "10:00"
}, {
    "day": 20.0
    , "fajir": "4:37"
    , "fajirIqamah": "5:00"
    , "sunrise": "6:13"
    , "duhur": "1:13"
    , "duhurIqamah": "1:30"
    , "asr": "5:04"
    , "asrIqamah": "5:30"
    , "maghrib": "8:17"
    , "maghribIqamah": "8:30"
    , "isha": "9:47"
    , "ishaIqamah": "10:00"
}, {
    "day": 21.0
    , "fajir": "4:38"
    , "fajirIqamah": "5:05"
    , "sunrise": "6:14"
    , "duhur": "1:12"
    , "duhurIqamah": "1:30"
    , "asr": "5:03"
    , "asrIqamah": "5:30"
    , "maghrib": "8:15"
    , "maghribIqamah": "8:20"
    , "isha": "9:45"
    , "ishaIqamah": "10:00"
}, {
    "day": 22.0
    , "fajir": "4:40"
    , "fajirIqamah": "5:05"
    , "sunrise": "6:15"
    , "duhur": "1:12"
    , "duhurIqamah": "1:30"
    , "asr": "5:02"
    , "asrIqamah": "5:30"
    , "maghrib": "8:13"
    , "maghribIqamah": "8:20"
    , "isha": "9:42"
    , "ishaIqamah": "10:00"
}, {
    "day": 23.0
    , "fajir": "4:42"
    , "fajirIqamah": "5:05"
    , "sunrise": "6:17"
    , "duhur": "1:12"
    , "duhurIqamah": "1:30"
    , "asr": "5:01"
    , "asrIqamah": "5:30"
    , "maghrib": "8:11"
    , "maghribIqamah": "8:20"
    , "isha": "9:40"
    , "ishaIqamah": "10:00"
}, {
    "day": 24.0
    , "fajir": "4:44"
    , "fajirIqamah": "5:25"
    , "sunrise": "6:18"
    , "duhur": "1:12"
    , "duhurIqamah": "1:30"
    , "asr": "5:00"
    , "asrIqamah": "5:30"
    , "maghrib": "8:09"
    , "maghribIqamah": "8:20"
    , "isha": "9:38"
    , "ishaIqamah": "9:40"
}, {
    "day": 25.0
    , "fajir": "4:46"
    , "fajirIqamah": "5:25"
    , "sunrise": "6:19"
    , "duhur": "1:11"
    , "duhurIqamah": "1:30"
    , "asr": "4:59"
    , "asrIqamah": "5:30"
    , "maghrib": "8:07"
    , "maghribIqamah": "8:20"
    , "isha": "9:35"
    , "ishaIqamah": "9:40"
}, {
    "day": 26.0
    , "fajir": "4:48"
    , "fajirIqamah": "5:25"
    , "sunrise": "6:20"
    , "duhur": "1:11"
    , "duhurIqamah": "1:30"
    , "asr": "4:58"
    , "asrIqamah": "5:30"
    , "maghrib": "8:05"
    , "maghribIqamah": "8:10"
    , "isha": "9:33"
    , "ishaIqamah": "9:40"
}, {
    "day": 27.0
    , "fajir": "4:49"
    , "fajirIqamah": "5:25"
    , "sunrise": "6:22"
    , "duhur": "1:11"
    , "duhurIqamah": "1:30"
    , "asr": "4:57"
    , "asrIqamah": "5:30"
    , "maghrib": "8:03"
    , "maghribIqamah": "8:10"
    , "isha": "9:31"
    , "ishaIqamah": "9:40"
}, {
    "day": 28.0
    , "fajir": "4:51"
    , "fajirIqamah": "5:25"
    , "sunrise": "6:23"
    , "duhur": "1:10"
    , "duhurIqamah": "1:30"
    , "asr": "4:56"
    , "asrIqamah": "5:30"
    , "maghrib": "8:02"
    , "maghribIqamah": "8:10"
    , "isha": "9:28"
    , "ishaIqamah": "9:30"
}, {
    "day": 29.0
    , "fajir": "4:53"
    , "fajirIqamah": "5:25"
    , "sunrise": "6:25"
    , "duhur": "1:10"
    , "duhurIqamah": "1:30"
    , "asr": "4:55"
    , "asrIqamah": "5:30"
    , "maghrib": "8:00"
    , "maghribIqamah": "8:10"
    , "isha": "9:26"
    , "ishaIqamah": "9:30"
}, {
    "day": 30.0
    , "fajir": "4:55"
    , "fajirIqamah": "5:25"
    , "sunrise": "6:26"
    , "duhur": "1:10"
    , "duhurIqamah": "1:30"
    , "asr": "4:53"
    , "asrIqamah": "5:30"
    , "maghrib": "7:58"
    , "maghribIqamah": "8:10"
    , "isha": "9:24"
    , "ishaIqamah": "9:30"
}, {
    "day": 31.0
    , "fajir": "4:56"
    , "fajirIqamah": "5:25"
    , "sunrise": "6:27"
    , "duhur": "1:09"
    , "duhurIqamah": "1:30"
    , "asr": "4:52"
    , "asrIqamah": "5:30"
    , "maghrib": "7:56"
    , "maghribIqamah": "8:10"
    , "isha": "9:21"
    , "ishaIqamah": "9:30"
}]